{"anubhav":[{"title":"test","desc":"asdasdasd13","date":1582144768434,"id":4},{"title":"asdasd","desc":"askjdhaskjasd","date":1582177026478,"id":6},{"title":"dfg","desc":"dfg","date":1582178003932,"id":8},{"title":"dfgdfg","desc":"dfgdfg","date":1582178007131,"id":9},{"title":"dfgkdfjg","desc":"skjdfjk","date":1582178011978,"id":10},{"title":"s;dfjsdj","desc":"lk;sjdflk","date":1582178016570,"id":11},{"title":"slk;djffj","desc":"kjkjlk","date":1582178021153,"id":12},{"title":"lkjkljlk","desc":"lkjlk;\n","date":1582178028078,"id":13},{"title":"sdkjfksjdfl","desc":"lkjlksjdfl\n","date":1582178032730,"id":14},{"title":"aslkdjaklsjd","desc":"lkjsklfdjlksdfa\n","date":1582178037672,"id":15},{"title":"asdjjkashd","desc":"skjjksd\n","date":1582178044495,"id":16},{"title":"askdjh","desc":"lkasjdlk","date":1582178096897,"id":17},{"title":"anubha","desc":"anubhav","date":1582180649224,"id":18}]}